suckscrypt/__init__.py
suckscrypt/core.py
SuckSCrypt-2.0.dist-info/METADATA
SuckSCrypt-2.0.dist-info/WHEEL
SuckSCrypt-2.0.dist-info/top_level.txt
SuckSCrypt-2.0.dist-info/RECORD
