Metadata-Version: 2.1
Name: SuckSCrypt
Version: 2.0
Summary: A Fastest & Secure Encryption System.
Home-page: https://github.com/IT-Club-SMKN-21-Jakarta/SuckSCrypt
Author: KyzuneX
Author-email: kyzunex@gmail.com
Classifier: Programming Language :: Python :: 3
Classifier: License :: OSI Approved :: MIT License
Classifier: Operating System :: OS Independent
Requires-Python: >=3.6
Requires-Dist: numpy
Requires-Dist: pycryptodome
Requires-Dist: pyarmor
